markitdown_reference_image/__init__.py
markitdown_reference_image/__main__.py
markitdown_reference_image/core.py
markitdown_reference_image/image_processor.py
markitdown_reference_image/text_finder.py
markitdown_reference_image/examples/__init__.py
markitdown_reference_image/examples/basic_extraction.py
markitdown_reference_image/examples/batch_processing.py
markitdown_reference_image/examples/cli_basic.py
markitdown_reference_image/examples/cli_custom_styling.py
markitdown_reference_image/examples/cli_with_score.py
markitdown_reference_image/examples/component_usage.py
markitdown_reference_image/examples/custom_styling.py
markitdown_reference_image/examples/error_handling.py
markitdown_reference_image/examples/improved_positioning.py
markitdown_reference_image/examples/multiline_text_example.py
markitdown_reference_image/examples/with_score.py
markitdown_reference_image/tests/__init__.py
markitdown_reference_image/tests/conftest.py
markitdown_reference_image/tests/test_main.py
markitdown_reference_image-0.1.0.dist-info/licenses/LICENSE
markitdown_reference_image-0.1.0.dist-info/METADATA
markitdown_reference_image-0.1.0.dist-info/WHEEL
markitdown_reference_image-0.1.0.dist-info/entry_points.txt
markitdown_reference_image-0.1.0.dist-info/top_level.txt
markitdown_reference_image-0.1.0.dist-info/RECORD
