Metadata-Version: 2.4
Name: markitdown-reference-image
Version: 0.1.0
Summary: Extract images from markdown files and highlight text chunks with bounding boxes
Home-page: https://github.com/yourusername/markitdown-reference-image
Author: Naveen Kumar Rajarajan
Author-email: Naveen Kumar Rajarajan <smazeeapps@gmail.com>
License: MIT
Project-URL: Homepage, https://github.com/yourusername/markitdown-reference-image
Project-URL: Repository, https://github.com/yourusername/markitdown-reference-image
Project-URL: Issues, https://github.com/yourusername/markitdown-reference-image/issues
Keywords: markitdown,image,reference
Classifier: Development Status :: 3 - Alpha
Classifier: Intended Audience :: Developers
Classifier: License :: OSI Approved :: MIT License
Classifier: Programming Language :: Python :: 3
Classifier: Programming Language :: Python :: 3.7
Classifier: Programming Language :: Python :: 3.8
Classifier: Programming Language :: Python :: 3.9
Classifier: Programming Language :: Python :: 3.10
Classifier: Programming Language :: Python :: 3.11
Requires-Python: >=3.7
License-File: LICENSE
Requires-Dist: Pillow>=8.0.0
Requires-Dist: markdown>=3.0.0
Requires-Dist: beautifulsoup4>=4.9.0
Requires-Dist: selenium>=4.0.0
Requires-Dist: webdriver-manager>=3.8.0
Provides-Extra: dev
Requires-Dist: pytest>=6.0; extra == "dev"
Requires-Dist: pytest-cov; extra == "dev"
Requires-Dist: black; extra == "dev"
Requires-Dist: flake8; extra == "dev"
Requires-Dist: mypy; extra == "dev"
Dynamic: author
Dynamic: home-page
Dynamic: license-file
Dynamic: requires-python
